statsig_openfeature_provider_python/__init__.py
statsig_openfeature_provider_python/provider.py
statsig_openfeature_provider_python/statsig.py
statsig_openfeature_provider_python-1.0.0.dist-info/METADATA
statsig_openfeature_provider_python-1.0.0.dist-info/WHEEL
statsig_openfeature_provider_python-1.0.0.dist-info/licenses/LICENSE
statsig_openfeature_provider_python-1.0.0.dist-info/RECORD
