Metadata-Version: 2.4
Name: statsig-openfeature-provider-python
Version: 1.0.0
Summary: Add your description here
License-File: LICENSE
Requires-Python: >=3.10
Requires-Dist: openfeature-sdk>=0.8.3
Requires-Dist: statsig-python-core>=0.11.1
